[
    {
        "version": "0.1.68",
        "releaseDate": "2016-12-07 08:10:25",
        "releaseTimestamp": "1481098225",
        "hash": "c695a1212a43c31d0d9ec2399d161a0c154302ea",
        "commits": [
            "[2016-12-07] Bumped version to 0.1.68",
            "[2016-12-07] Feature: display products & domains summary in orders search"
        ]
    },
    {
        "version": "0.1.67",
        "releaseDate": "2016-12-07 07:46:10",
        "releaseTimestamp": "1481096770",
        "hash": "c6760907bf55e66b2e223f8ab70e0a751bc4c4f8",
        "commits": [
            "[2016-12-07] Bumped version to 0.1.67",
            "[2016-12-07] Feature: validate domains on frontend",
            "[2016-12-07] Feature: validate domains on frontend"
        ]
    },
    {
        "version": "0.1.66",
        "releaseDate": "2016-12-07 04:49:38",
        "releaseTimestamp": "1481086178",
        "hash": "c0c3499fc240b275a7968ab4a28368875773abfd",
        "commits": [
            "[2016-12-07] Bumped version to 0.1.66",
            "[2016-12-07] Feature: validate domains on frontend"
        ]
    },
    {
        "version": "0.1.65",
        "releaseDate": "2016-12-07 04:08:28",
        "releaseTimestamp": "1481083708",
        "hash": "d9b022881bd39af497171e7ceb6f53dec96dcae7",
        "commits": [
            "[2016-12-07] Bumped version to 0.1.65",
            "[2016-12-07] Feature: validate domains on frontend",
            "[2016-12-07] Feature: allow customers to update development domains attached to their licenses",
            "[2016-12-07] Feature: allow customers to update development domains attached to their licenses",
            "[2016-12-07] Bugfix: editing order in backend, wrongfully generated new license keys (instead, it should have just updated the license's status to inactive)",
            "[2016-12-07] Bugfix: editing order in backend, wrongfully generated new license keys (instead, it should have just updated the license's status to inactive)"
        ]
    }
]